druidaHFSS/Manager.py
druidaHFSS/__init__.py
druidaHFSS/globals.py
druidaHFSS/modules/__init__.py
druidaHFSS/modules/hfss.py
druidaHFSS/modules/tools.py
druidahfss-0.0.3.dist-info/METADATA
druidahfss-0.0.3.dist-info/WHEEL
druidahfss-0.0.3.dist-info/RECORD
