Metadata-Version: 2.3
Name: druidaHFSS
Version: 0.0.3
Summary: Ansys interface for Data Generation
Project-URL: Homepage, https://github.com/Jorgecardenas1/dbGeneration_v0
Author-email: Jorge Cardenas <jorge.cardenas.l@mail.pucv.cl>
Classifier: License :: OSI Approved :: MIT License
Classifier: Operating System :: OS Independent
Classifier: Programming Language :: Python :: 3
Requires-Python: >=3.7
Requires-Dist: imutils
Requires-Dist: numpy<=1.24.3
Requires-Dist: opencv-python
Requires-Dist: pandas~=2.1.0
Requires-Dist: pillow
Requires-Dist: scikit-learn
Requires-Dist: torch
Requires-Dist: wheel
